pawflim/__init__.py
pawflim/tests/test_pawflim.py
pawflim-1.0.4.dist-info/LICENSE
pawflim-1.0.4.dist-info/METADATA
pawflim-1.0.4.dist-info/WHEEL
pawflim-1.0.4.dist-info/top_level.txt
pawflim-1.0.4.dist-info/RECORD
