Metadata-Version: 2.1
Name: pawflim
Version: 1.0.4
Summary: Denoising via adaptive binning for FLIM datasets.
Author-email: Mauro Silberberg <maurosilber@gmail.com>
License: MIT License
Project-URL: Homepage, https://github.com/maurosilber/pawflim
Project-URL: Bug Tracker, https://github.com/maurosilber/pawflim/issues
Keywords: FLIM,pawFLIM,binlets,denoising,adaptive,wavelets
Classifier: Programming Language :: Python :: 3
Classifier: License :: OSI Approved :: MIT License
Classifier: Operating System :: OS Independent
Classifier: Intended Audience :: Developers
Classifier: Intended Audience :: Science/Research
Classifier: Topic :: Scientific/Engineering
Classifier: Topic :: Software Development :: Libraries
Requires-Python: >=3.7
License-File: LICENSE
Requires-Dist: binlets >=1
Requires-Dist: numpy
Requires-Dist: scipy
Provides-Extra: test
Requires-Dist: hypothesis ; extra == 'test'
Requires-Dist: pytest ; extra == 'test'
